{
  "profile": "confirmatory",
  "dev_only": false,
  "protocol_version": "exp29_confirmatory_selector_v1_fixed_meta",
  "confirmatory_readiness": "ready",
  "required_run_label": "exp29-confirmatory-selector-v1",
  "inference_status": "preregistered_confirmatory",
  "confirmatory_eligible": true,
  "implementation_binding": {
    "schema_version": "exp29_selector_implementation_binding_v1",
    "runner_path": "experiments/exp29_confirmatory_actuator_selector.py",
    "runner_normalized_sha256": "575ecc2169474261de7e53164a4cea89313b526e18f28476aa375b03d51b866f",
    "summarizer_path": "scripts/summarize_exp29_selector.py",
    "summarizer_normalized_sha256": "69efc05687569ee5ac999c50b99b41143839af80cd526885cc9a96896ac6d90d"
  },
  "selector_fit_seed": 2801,
  "meta_training_seeds": [
    0, 1, 2, 3, 4, 5, 6, 7, 8, 9,
    10, 11, 12, 13, 14, 15, 16, 17, 18, 19,
    20, 21, 22, 23, 24, 25, 26, 27, 28, 29
  ],
  "evaluation_seeds": [
    60, 61, 62, 63, 64, 65, 66, 67, 68, 69,
    70, 71, 72, 73, 74, 75, 76, 77, 78, 79,
    80, 81, 82, 83, 84, 85, 86, 87, 88, 89
  ],
  "registered_heldout_generators": [
    {"generator_id": "0bd7af7832db15eb44cc", "alpha": 0.8, "transition_rank": 2, "input_rank": 2, "delay": 12.0, "noise_std": 1.0},
    {"generator_id": "10b0d8f1ae8181a6281a", "alpha": 0.1, "transition_rank": 2, "input_rank": 1, "delay": 4.0, "noise_std": 0.3},
    {"generator_id": "15a2310ac4a6d678e486", "alpha": 0.5, "transition_rank": 8, "input_rank": 1, "delay": 12.0, "noise_std": 0.6},
    {"generator_id": "15b5875c0310fa4180c9", "alpha": 0.3, "transition_rank": 2, "input_rank": 4, "delay": 4.0, "noise_std": 1.0},
    {"generator_id": "1936891e6bd2b265f22b", "alpha": 0.5, "transition_rank": 2, "input_rank": 2, "delay": 4.0, "noise_std": 0.3},
    {"generator_id": "196ff599d1627b1299d2", "alpha": 0.2, "transition_rank": 2, "input_rank": 4, "delay": 0.0, "noise_std": 0.6},
    {"generator_id": "23376f20f6841604c117", "alpha": 0.7, "transition_rank": 8, "input_rank": 2, "delay": 4.0, "noise_std": 0.3},
    {"generator_id": "2bdf2e1434739caf8201", "alpha": 0.0, "transition_rank": 1, "input_rank": 2, "delay": 4.0, "noise_std": 0.6},
    {"generator_id": "2e5836fad2bc41fb118b", "alpha": 0.1, "transition_rank": 8, "input_rank": 1, "delay": 12.0, "noise_std": 1.0},
    {"generator_id": "3266bbb8526e12299583", "alpha": 1.0, "transition_rank": 8, "input_rank": 4, "delay": 0.0, "noise_std": 0.3},
    {"generator_id": "341d3e9ccd5f87e91641", "alpha": 0.4, "transition_rank": 8, "input_rank": 1, "delay": 4.0, "noise_std": 0.1},
    {"generator_id": "3abf14245835af11ec21", "alpha": 0.5, "transition_rank": 1, "input_rank": 4, "delay": 12.0, "noise_std": 0.6},
    {"generator_id": "3c47eeea7c2680fcc25b", "alpha": 0.9, "transition_rank": 1, "input_rank": 2, "delay": 12.0, "noise_std": 0.3},
    {"generator_id": "4086461a4203328bd16e", "alpha": 0.3, "transition_rank": 4, "input_rank": 4, "delay": 24.0, "noise_std": 0.3},
    {"generator_id": "4109b4a1f9d61884c2da", "alpha": 0.4, "transition_rank": 1, "input_rank": 1, "delay": 0.0, "noise_std": 1.0},
    {"generator_id": "42b8f12c0c5950d92999", "alpha": 0.5, "transition_rank": 4, "input_rank": 2, "delay": 24.0, "noise_std": 0.1},
    {"generator_id": "456ec9e64e5a1a3d9f93", "alpha": 0.9, "transition_rank": 2, "input_rank": 1, "delay": 4.0, "noise_std": 0.1},
    {"generator_id": "45abc0a8b69fa13f3674", "alpha": 0.6, "transition_rank": 1, "input_rank": 1, "delay": 0.0, "noise_std": 0.3},
    {"generator_id": "47c1410c004953eb0280", "alpha": 0.0, "transition_rank": 4, "input_rank": 2, "delay": 0.0, "noise_std": 1.0},
    {"generator_id": "5d288e781e3d2176865a", "alpha": 0.4, "transition_rank": 2, "input_rank": 1, "delay": 24.0, "noise_std": 0.3},
    {"generator_id": "6c8b9987b26988e5530f", "alpha": 1.0, "transition_rank": 1, "input_rank": 1, "delay": 4.0, "noise_std": 0.6},
    {"generator_id": "6d50188fd2dc0b2cc0a5", "alpha": 0.9, "transition_rank": 4, "input_rank": 4, "delay": 24.0, "noise_std": 0.6},
    {"generator_id": "6da7437f8db9b9c3f436", "alpha": 1.0, "transition_rank": 2, "input_rank": 4, "delay": 12.0, "noise_std": 0.6},
    {"generator_id": "7b8779953b55d87d1844", "alpha": 0.6, "transition_rank": 1, "input_rank": 4, "delay": 24.0, "noise_std": 0.6},
    {"generator_id": "8530ec77868b80eeae89", "alpha": 0.2, "transition_rank": 1, "input_rank": 1, "delay": 0.0, "noise_std": 0.3},
    {"generator_id": "8a9e90418f83abc02006", "alpha": 0.8, "transition_rank": 8, "input_rank": 1, "delay": 24.0, "noise_std": 1.0},
    {"generator_id": "8cbdd2180b7f04c1b336", "alpha": 0.7, "transition_rank": 2, "input_rank": 4, "delay": 0.0, "noise_std": 0.6},
    {"generator_id": "9cfe41132d5aa8cf41c5", "alpha": 0.2, "transition_rank": 4, "input_rank": 2, "delay": 24.0, "noise_std": 1.0},
    {"generator_id": "9e7ebd3b39c6bcc1c4fc", "alpha": 0.4, "transition_rank": 4, "input_rank": 4, "delay": 0.0, "noise_std": 0.1},
    {"generator_id": "aca719999ebff575e2a2", "alpha": 0.3, "transition_rank": 1, "input_rank": 2, "delay": 24.0, "noise_std": 0.1},
    {"generator_id": "b07ad834df7008d8c036", "alpha": 0.7, "transition_rank": 1, "input_rank": 2, "delay": 0.0, "noise_std": 0.1},
    {"generator_id": "c6089c719fde5878c2a8", "alpha": 0.3, "transition_rank": 8, "input_rank": 2, "delay": 4.0, "noise_std": 0.6},
    {"generator_id": "c6409e9be385d65f2f61", "alpha": 0.7, "transition_rank": 4, "input_rank": 2, "delay": 24.0, "noise_std": 0.6},
    {"generator_id": "caf4bc3dbe0d0521b2d5", "alpha": 0.6, "transition_rank": 8, "input_rank": 1, "delay": 12.0, "noise_std": 1.0},
    {"generator_id": "d2165cab3f486af884f9", "alpha": 1.0, "transition_rank": 8, "input_rank": 1, "delay": 12.0, "noise_std": 1.0},
    {"generator_id": "d742cddcc10eab71a794", "alpha": 0.1, "transition_rank": 1, "input_rank": 4, "delay": 4.0, "noise_std": 0.1},
    {"generator_id": "ddce512975cdaeb696ed", "alpha": 0.0, "transition_rank": 2, "input_rank": 1, "delay": 24.0, "noise_std": 0.3},
    {"generator_id": "e2a1346c0aef297aedc2", "alpha": 0.1, "transition_rank": 4, "input_rank": 4, "delay": 12.0, "noise_std": 0.6},
    {"generator_id": "e3caec5f6e01363ba78b", "alpha": 0.8, "transition_rank": 4, "input_rank": 1, "delay": 4.0, "noise_std": 0.1},
    {"generator_id": "e6fa22f8fab42439c614", "alpha": 0.8, "transition_rank": 4, "input_rank": 2, "delay": 24.0, "noise_std": 0.3},
    {"generator_id": "ea44d2864e25bfd2e82e", "alpha": 0.2, "transition_rank": 8, "input_rank": 2, "delay": 12.0, "noise_std": 0.1},
    {"generator_id": "fd0054c6759ff72ba9d7", "alpha": 0.6, "transition_rank": 4, "input_rank": 4, "delay": 0.0, "noise_std": 1.0},
    {"generator_id": "fd1fffd894c5dceb1bd8", "alpha": 0.0, "transition_rank": 8, "input_rank": 4, "delay": 12.0, "noise_std": 0.1},
    {"generator_id": "fecf485b3a2cbb44ff25", "alpha": 0.9, "transition_rank": 2, "input_rank": 4, "delay": 0.0, "noise_std": 1.0}
  ],
  "training_algorithm": "single_fixed_meta_selector_fit_then_one_shot_confirmatory_test",
  "used_autograd": false,
  "used_bptt": false,
  "dictionary": ["routing", "gain", "low_rank"],
  "selectors": ["oracle", "gru_bptt", "local_three_factor", "fixed_best"],
  "decision_modes": ["frozen", "routing", "gain", "low_rank"],
  "feature_columns": [
    "chi", "state_demand", "input_demand", "transition_rank",
    "input_rank", "delay", "noise_std"
  ],
  "feature_transform": {
    "cues": ["demand", "ranks", "timing_noise"],
    "raw_to_transformed": {
      "chi": "identity",
      "state_demand": "log",
      "input_demand": "log",
      "transition_rank": "log2",
      "input_rank": "log2",
      "delay": "scaled",
      "noise_std": "log"
    },
    "include_bias": true,
    "fit_scope": "exp26_meta_seeds_0_29_discovery_validation_only"
  },
  "source_exp26_meta": {
    "raw_metrics_path": "results/exp26_actuator_matching_formal_v2_e08beaf/formal/raw_metrics.csv.gz",
    "conclusion_path": "results/exp26_actuator_matching_formal_v2_e08beaf/formal/conclusion.json",
    "expected_raw_metrics_sha256": "b3ef5e22c241f832b1fd50254f87e3890ec45057bfeda3a784cbd218623a1193",
    "expected_conclusion_sha256": "2038127ac875f9faae94b305343415b8fb3a794f9ea032f017401e432fa9d40f",
    "expected_config_sha256": "07ad3f16d9de6b5906155d95f215e9434e478ca992fd023adfabcd21a0005ecf",
    "expected_manifest_sha256": "a1c17a1e88c731f6678760865cf51d7236ae771bf839645c401e5cff8798ebfa",
    "required_profile": "formal",
    "required_conclusion": "support"
  },
  "confirmatory_source_package": {
    "package_dir": "/home/spco/sow_linear/exp29_confirmatory_source_v1_94fa1c8/package",
    "registered_source_config_path": "configs/formal/exp29_confirmatory_source_panel.json",
    "expected_source_panel_receipt_file_sha256": "45fe29a75150e25ce8d292288ddfdbaa9d54f05812beeb53a3eabafa5b618684",
    "expected_conclusion_file_sha256": "f9e7ce8325e3f9906bc0974380ef11e7cdbec05888bdfde07ea7e46de3d1efd0",
    "expected_raw_metrics_sha256": "a5708c123c5d1ba9486fa190c3517b6fb29f4a8d454024d965db42e0058a6818",
    "expected_receipt_payload_sha256": "64a5bf3d11e82dca491f7c98fb7af7be898715af75927d616909876b886c5a43",
    "expected_registered_config_sha256": "70db02c9e578ace8a1719e4ff6c71c07048a1836f2dafc9fcd845ad5b0bd9e14",
    "expected_registered_config_file_sha256": "a058e175d2634cbcb0dde68e1709904c897f51ec8055fe9de666b0e1cffd7500",
    "expected_source_contract_sha256": "f548724759f2b95a862feca564dfc9897a7356ee81ac949b20f0106077e689c3",
    "expected_package_schema_version": "exp29_confirmatory_source_package_v1",
    "expected_source_protocol_version": "exp29_confirmatory_source_v1",
    "expected_evidence_schema_version": "exp29_confirmatory_source_evidence_v1",
    "expected_experiment": "exp29_confirmatory_source_panel",
    "expected_profile": "confirmatory_test",
    "expected_evidence_role": "confirmatory_test_source_only",
    "expected_source_conclusion": "inconclusive",
    "expected_standalone_inference_performed": false,
    "expected_standalone_inference_permitted": false,
    "expected_source_panel_valid": true
  },
  "local_selector": {
    "epochs": 200,
    "learning_rate": 0.05,
    "temperature": 1.0,
    "teacher_temperature": 0.05,
    "l2": 0.0001,
    "eligibility_decay": 0.8,
    "belief_retention": 0.8
  },
  "gru_selector": {
    "hidden_dim": 8,
    "epochs": 200,
    "learning_rate": 0.02,
    "weight_decay": 0.0001,
    "teacher_temperature": 0.05,
    "device": "cpu",
    "deterministic": true
  },
  "evaluation": {
    "train_generator_split": "discovery",
    "train_endpoint": "validation_balanced_accuracy",
    "test_generator_split": "heldout",
    "test_endpoint": "test_balanced_accuracy_with_frozen_fallback",
    "statistics_unit": "evaluation_seed",
    "primary_scope": "unconditional_all_registered_heldout_cells",
    "tie_break_order": ["frozen", "routing", "gain", "low_rank"],
    "local_oracle_gain_fraction_threshold": 0.8,
    "expected_heldout_generators_per_seed": 44,
    "matched_budget_support_requires_feasible_active_row": true,
    "unexpected_failure_conclusion": "invalid"
  },
  "analysis": {
    "bootstrap_samples": 20000,
    "permutation_samples": 100000,
    "confidence": 0.95,
    "statistics_seed": 2901,
    "multiple_comparison_correction": "holm",
    "alpha": 0.05
  }
}
